ActiveCollab/ActiveCollab.py
ActiveCollab/ActiveCollab_old.py
ActiveCollab/__init__.py
ActiveCollab-3.7.dist-info/LICENSE
ActiveCollab-3.7.dist-info/METADATA
ActiveCollab-3.7.dist-info/WHEEL
ActiveCollab-3.7.dist-info/top_level.txt
ActiveCollab-3.7.dist-info/RECORD
