Metadata-Version: 2.1
Name: ActiveCollab
Version: 3.7
Summary: A python library working with activeCollab
Author-email: Ankush Kumar <ankush1611996@gmail.com>
Project-URL: Homepage, https://github.com/AnkushRozra/ActiveCollab
Project-URL: Bug Tracker, https://github.com/AnkushRozra/ActiveCollab/issues
Keywords: Active Collab,ActiveCollab,Active Collab SDK,active collab
Classifier: Programming Language :: Python :: 3
Classifier: License :: OSI Approved :: MIT License
Classifier: Operating System :: OS Independent
Requires-Python: >=3.8
License-File: LICENSE
Requires-Dist: requests
Requires-Dist: sys
